leetcode_data_structure/__init__.py
leetcode_data_structure/binary_tree.py
leetcode_data_structure/link_list.py
leetcode_data_structure/nary_tree.py
leetcode_data_structure/py.typed
leetcode_data_structure-0.1.2.dist-info/LICENSE
leetcode_data_structure-0.1.2.dist-info/METADATA
leetcode_data_structure-0.1.2.dist-info/WHEEL
leetcode_data_structure-0.1.2.dist-info/top_level.txt
leetcode_data_structure-0.1.2.dist-info/RECORD
