Metadata-Version: 2.1
Name: leetcode-data-structure
Version: 0.1.2
Summary: This package provides three classes for working with data structures in LeetCode problems
Home-page: https://github.com/EricWebsmith/leetcode_data_structure
Author: Eric Websmith
Author-email: eric.websmith@example.com
Classifier: Programming Language :: Python :: 3
Classifier: License :: OSI Approved :: MIT License
Classifier: Operating System :: OS Independent
Requires-Python: >=3.10
License-File: LICENSE
